emailverify/__init__.py
emailverify/client.py
emailverify/exceptions.py
emailverify/types.py
emailverify_ai-1.0.2.dist-info/METADATA
emailverify_ai-1.0.2.dist-info/WHEEL
emailverify_ai-1.0.2.dist-info/RECORD
