Metadata-Version: 2.4
Name: emailverify-ai
Version: 1.0.2
Summary: Official EmailVerify Python SDK for email verification
Project-URL: Homepage, https://emailverify.ai
Project-URL: Documentation, https://emailverify.ai/docs
Project-URL: Repository, https://github.com/emailverify-ai/python-sdk
Author-email: EmailVerify <support@emailverify.ai>
License-Expression: MIT
Keywords: email,email-verification,emailverify,validation,verification
Classifier: Development Status :: 5 - Production/Stable
Classifier: Intended Audience :: Developers
Classifier: License :: OSI Approved :: MIT License
Classifier: Operating System :: OS Independent
Classifier: Programming Language :: Python :: 3
Classifier: Programming Language :: Python :: 3.8
Classifier: Programming Language :: Python :: 3.9
Classifier: Programming Language :: Python :: 3.10
Classifier: Programming Language :: Python :: 3.11
Classifier: Programming Language :: Python :: 3.12
Classifier: Typing :: Typed
Requires-Python: >=3.8
Requires-Dist: httpx>=0.24.0
Provides-Extra: dev
Requires-Dist: mypy>=1.0; extra == 'dev'
Requires-Dist: pytest-asyncio>=0.21; extra == 'dev'
Requires-Dist: pytest>=7.0; extra == 'dev'
Requires-Dist: ruff>=0.1; extra == 'dev'
